{
  "sections": {
    "collection-head": {
      "type": "collection-head",
      "settings": {
      }
    },
    "product-grid": {
      "type": "main-collection-product-filter-custom",
      "blocks": {
        "9358f901-84bd-4122-80ec-5388094f7298": {
          "type": "filter",
          "settings": {
            "filter_name": "Accessoires",
            "filter_tag1": "Bereiding",
            "filter_tag2": "Servering",
            "filter_tag3": "Bewaren",
            "filter_tag4": "",
            "filter_tag5": "",
            "filter_tag6": "",
            "filter_tag7": "",
            "filter_tag8": ""
          }
        }
      },
      "block_order": [
        "9358f901-84bd-4122-80ec-5388094f7298"
      ],
      "settings": {
      }
    },
    "16340230414b0d66a6": {
      "type": "cookie-popup",
      "settings": {
        "header_text": "Have a cookie next to your tea or coffee",
        "sub_header_text": "Lorem ipsum dolor sit amet, consectetur adipiscing elit. Sed at dapibus elit. Maecenas ut mauris mattis, eleifend."
      }
    }
  },
  "order": [
    "collection-head",
    "product-grid",
    "16340230414b0d66a6"
  ]
}
